{
  "obsidian-california-coast-theme@@editor-line-height": 1.4,
  "obsidian-california-coast-theme@@cc-em-strong": false,
  "obsidian-california-coast-theme@@h1-margin-top": 1,
  "obsidian-california-coast-theme@@h1-margin-bottom": 0.5,
  "obsidian-california-coast-theme@@h2-margin-top": 0.75,
  "obsidian-california-coast-theme@@h3-margin-top": 0.75,
  "obsidian-california-coast-theme@@h4-margin-top": 1,
  "obsidian-california-coast-theme@@h5-margin-top": 1,
  "obsidian-california-coast-theme@@h6-margin-top": 1,
  "obsidian-california-coast-theme@@h2-weight": 500,
  "obsidian-california-coast-theme@@h3-weight": 500,
  "obsidian-california-coast-theme@@accent": "#5D0799",
  "obsidian-california-coast-theme@@line-width": 50,
  "obsidian-california-coast-theme@@cc-editor-heading-hash": false,
  "perso@@black-background-sidebar": false,
  "perso@@menus": "menu-v1",
  "perso@@writing-focus": true,
  "perso@@img-box-shadow": true,
  "perso@@outline-mode": true,
  "perso@@writing-focus-opacity": 0.82,
  "minimal-style@@h4-variant": "normal",
  "minimal-style@@h4-l": false,
  "minimal-style@@h1-l": true,
  "minimal-style@@h4-weight": 600,
  "minimal-style@@minimal-strike-lists": false,
  "shimmering-focus@@hide-settings-button": false,
  "shimmering-focus@@show-titlebar": true,
  "obsidian-california-coast-theme@@cc-no-custom-icons": false,
  "things-style@@max-width": 100,
  "things-style@@line-width": 70,
  "blue-topaz-theme@@translucent-setting-panel": false,
  "blue-topaz-theme@@circular-checkbox": false,
  "blue-topaz-theme@@style-options-for-admonition-plugin": true,
  "primary-ceciliamay@@note-embeds__style": "note-embeds__style-original",
  "primary-ceciliamay@@full-height-embeds": true,
  "primary-ceciliamay@@center-embeds": false,
  "primary-ceciliamay@@no-link-underline": true,
  "blue-topaz-theme@@embed-title": true,
  "blue-topaz-theme@@embed-hd": false,
  "blue-topaz-theme@@embed-hover": true,
  "blue-topaz-theme@@naked-embed": false,
  "blue-topaz-theme@@h1-toggle-underline": false,
  "sanctum@@light-mode-palette": "sanctum-coldgrey",
  "shimmering-focus@@show-close-button": true,
  "shimmering-focus@@show-scrollbar": true,
  "shimmering-focus@@show-ribbons": true,
  "shimmering-focus@@preset-color-scheme": "classic-colors",
  "shimmering-focus@@brightness-light": 7,
  "ITS@@its-i": false,
  "ITS@@s-d": false,
  "ITS@@slrvb-g": false,
  "ITS@@slrvb-b": false,
  "ITS@@drwn": false,
  "ITS@@nord": false,
  "ITS@@mini": false,
  "ITS@@notion": true,
  "primary-ceciliamay@@scrollbar-style": "scrollbar__thin",
  "Willemstad-Core@@col-palette": "cp-exobs-nord",
  "Willemstad-Core@@headers-round": true,
  "Willemstad-Core@@sb": "default",
  "sanctum@@no-blur": false,
  "sanctum@@topside-status-bar": false,
  "sanctum@@dim-panes": false,
  "primary-ceciliamay@@header-color__preset": "header-color__rainbow",
  "primary-ceciliamay@@header-size__preset": "header-size__original",
  "minimal-cards-style@@cards-min-width": "80px",
  "primary-ceciliamay@@tab-header-style": "tab-header__style-original",
  "primary-ceciliamay@@tab-header__wrap": false,
  "supercharged-links@@2a1a-a601-before": "🧑 ",
  "supercharged-links@@2a1a-a601-decoration": "initial",
  "supercharged-links@@2a1a-a601-weight": "initial",
  "supercharged-links@@5c3b-5979-before": "👨‍💻 ",
  "supercharged-links@@321e-2cdf-before": "🤝🏼 ",
  "supercharged-links@@2a1a-a601-color": "#00A9CE",
  "supercharged-links@@5c3b-5979-color": "#B00A0A",
  "supercharged-links@@35b6-7fc7-color": "#E22323",
  "supercharged-links@@35b6-7fc7-before": "🏦 ",
  "supercharged-links@@6ad9-07ba-before": "💼 ",
  "supercharged-links@@6ad9-07ba-color": "#005B7F",
  "primary-ceciliamay@@h1-border": true
}